knowledge_engine/__init__.py
knowledge_engine/__main__.py
knowledge_engine/client.py
knowledge_engine-0.1.0.dist-info/METADATA
knowledge_engine-0.1.0.dist-info/WHEEL
knowledge_engine-0.1.0.dist-info/entry_points.txt
knowledge_engine-0.1.0.dist-info/top_level.txt
knowledge_engine-0.1.0.dist-info/RECORD
