Metadata-Version: 2.4
Name: knowledge-engine
Version: 0.1.0
Summary: Python SDK for the Knowledge Engine backend
Author: Knowledge Engine
License: MIT
Classifier: Programming Language :: Python :: 3
Classifier: License :: OSI Approved :: MIT License
Requires-Python: >=3.9
Provides-Extra: dev
Requires-Dist: pytest>=7.0; extra == "dev"
